phydisk/__init__.py
phydisk/linux.py
phydisk/macOS.py
phydisk/models.py
phydisk/squire.py
phydisk/windows.py
PhyDisk-0.1.0.dist-info/LICENSE
PhyDisk-0.1.0.dist-info/METADATA
PhyDisk-0.1.0.dist-info/WHEEL
PhyDisk-0.1.0.dist-info/entry_points.txt
PhyDisk-0.1.0.dist-info/top_level.txt
PhyDisk-0.1.0.dist-info/RECORD
