Metadata-Version: 2.1
Name: PhyDisk
Version: 0.1.0
Summary: Python module to get physical drives connected to a host machine
Author-email: Vignesh Rao <svignesh1793@gmail.com>
License: MIT License
Project-URL: Homepage, https://github.com/thevickypedia/PhyDisk
Project-URL: Source, https://github.com/thevickypedia/PhyDisk
Keywords: physical-drives,PhyDisk
Classifier: License :: OSI Approved :: MIT License
Classifier: Programming Language :: Python :: 3
Classifier: Development Status :: 5 - Production/Stable
Classifier: Operating System :: OS Independent
Classifier: Topic :: System :: Hardware
Requires-Python: >=3.10
License-File: LICENSE
Provides-Extra: dev
Requires-Dist: pre-commit; extra == "dev"
Provides-Extra: standard
Requires-Dist: Jinja2==3.1.*; extra == "standard"
Requires-Dist: requests==2.*; extra == "standard"
Requires-Dist: gmail-connector; extra == "standard"
